framat/__init__.py
framat/_assembly.py
framat/_element.py
framat/_log.py
framat/_meshing.py
framat/_model.py
framat/_plot.py
framat/_run.py
framat/_solve.py
framat/_util.py
framat-0.5.dist-info/licenses/LICENSE.txt
framat-0.5.dist-info/METADATA
framat-0.5.dist-info/WHEEL
framat-0.5.dist-info/top_level.txt
framat-0.5.dist-info/RECORD
