Metadata-Version: 2.4
Name: framat
Version: 0.5
Summary: FramAT (Frame Analysis Tool) is a tool for 3D FEM beam analyses
Home-page: https://github.com/airinnova/framat
Author: Aaron Dettmann
Author-email: dettmann@kth.se
License: Apache License 2.0
Classifier: Programming Language :: Python :: 3
Classifier: Programming Language :: Python :: 3.11
Classifier: License :: OSI Approved :: Apache Software License
Classifier: Operating System :: OS Independent
Classifier: Environment :: Console
Classifier: Intended Audience :: Developers
Classifier: Intended Audience :: Education
Classifier: Intended Audience :: Science/Research
Classifier: Topic :: Scientific/Engineering
Classifier: Topic :: Scientific/Engineering :: Physics
Requires-Python: >=3.6.0
License-File: LICENSE.txt
Requires-Dist: commonlibs>=0.3.3
Requires-Dist: jsonschema
Requires-Dist: matplotlib>=3.4.0
Requires-Dist: numpy
Requires-Dist: scipy
Requires-Dist: model-framework>=0.0.14
Dynamic: author
Dynamic: author-email
Dynamic: classifier
Dynamic: description
Dynamic: description-content-type
Dynamic: home-page
Dynamic: license
Dynamic: license-file
Dynamic: requires-dist
Dynamic: requires-python
Dynamic: summary
